is_subset/__init__.py
is_subset/helper.py
is_subset/py.typed
is_subset/subset.py
is_subset-0.1.1.dist-info/METADATA
is_subset-0.1.1.dist-info/WHEEL
is_subset-0.1.1.dist-info/licenses/LICENSE
is_subset-0.1.1.dist-info/RECORD
