Metadata-Version: 2.3
Name: is_subset
Version: 0.1.1
Summary: check if a given dictionary is subset of provided predicate
Project-URL: Repository, https://github.com/WajahatAliAbid/is-subset
Project-URL: Changelog, https://github.com/WajahatAliAbid/is-subset/blob/main/CHANGELOG.md
Author-email: WajahatAliAbid <17341777+WajahatAliAbid@users.noreply.github.com>
Keywords: is-subset,python,subset
Classifier: Intended Audience :: Developers
Classifier: License :: OSI Approved :: GNU General Public License v2 (GPLv2)
Classifier: Operating System :: MacOS :: MacOS X
Classifier: Operating System :: Microsoft :: Windows
Classifier: Operating System :: Unix
Classifier: Programming Language :: Python :: 3
Requires-Python: >=3.8
